adafruit_tsl2561.py
adafruit_circuitpython_tsl2561-3.3.23.dist-info/licenses/LICENSE
adafruit_circuitpython_tsl2561-3.3.23.dist-info/METADATA
adafruit_circuitpython_tsl2561-3.3.23.dist-info/WHEEL
adafruit_circuitpython_tsl2561-3.3.23.dist-info/top_level.txt
adafruit_circuitpython_tsl2561-3.3.23.dist-info/RECORD
